FFMPEG_Filters/Image.py
FFMPEG_Filters/__init__.py
ffmpeg_filters-10.0.dist-info/METADATA
ffmpeg_filters-10.0.dist-info/WHEEL
ffmpeg_filters-10.0.dist-info/top_level.txt
ffmpeg_filters-10.0.dist-info/RECORD
