Metadata-Version: 2.4
Name: FFMPEG_Filters
Version: 10.0
Summary: FFMPEG_Filters is a set of effects for images to create a video.
Home-page: https://github.com/Tgthegood1/FFMPEG_Filters
Author: Tgthegood
Author-email: almeidaaxel52@gmail.com
License: MIT
Classifier: Programming Language :: Python :: 3
Classifier: License :: OSI Approved :: MIT License
Classifier: Operating System :: OS Independent
Requires-Dist: Pillow
Dynamic: author
Dynamic: author-email
Dynamic: classifier
Dynamic: description
Dynamic: description-content-type
Dynamic: home-page
Dynamic: license
Dynamic: requires-dist
Dynamic: summary
